deltafq/__init__.py
deltafq/backtest/__init__.py
deltafq/backtest/engine.py
deltafq/backtest/metrics.py
deltafq/backtest/performance.py
deltafq/charts/__init__.py
deltafq/charts/performance.py
deltafq/charts/price.py
deltafq/charts/signals.py
deltafq/core/__init__.py
deltafq/core/base.py
deltafq/core/config.py
deltafq/core/logger.py
deltafq/data/__init__.py
deltafq/data/cleaner.py
deltafq/data/fetcher.py
deltafq/data/storage.py
deltafq/indicators/__init__.py
deltafq/indicators/fundamental.py
deltafq/indicators/talib_indicators.py
deltafq/indicators/technical.py
deltafq/live/__init__.py
deltafq/live/connection.py
deltafq/live/data_feed.py
deltafq/live/monitoring.py
deltafq/live/risk_control.py
deltafq/strategy/__init__.py
deltafq/strategy/base.py
deltafq/strategy/signals.py
deltafq/trader/__init__.py
deltafq/trader/broker.py
deltafq/trader/engine.py
deltafq/trader/order_manager.py
deltafq/trader/position_manager.py
deltafq-0.5.0.dist-info/licenses/LICENSE
deltafq-0.5.0.dist-info/METADATA
deltafq-0.5.0.dist-info/WHEEL
deltafq-0.5.0.dist-info/top_level.txt
deltafq-0.5.0.dist-info/RECORD
