Metadata-Version: 2.4
Name: deltafq
Version: 0.5.0
Summary: A comprehensive Python quantitative finance library
Author-email: DeltaF <leek_li@outlook.com>
License: MIT
Project-URL: Homepage, https://github.com/Delta-F/deltafq
Project-URL: Repository, https://github.com/Delta-F/deltafq
Project-URL: Issues, https://github.com/Delta-F/deltafq/issues
Classifier: Development Status :: 3 - Alpha
Classifier: Intended Audience :: Financial and Insurance Industry
Classifier: Intended Audience :: Developers
Classifier: License :: OSI Approved :: MIT License
Classifier: Programming Language :: Python :: 3.9
Classifier: Programming Language :: Python :: 3.10
Classifier: Programming Language :: Python :: 3.11
Classifier: Programming Language :: Python :: 3.12
Classifier: Topic :: Office/Business :: Financial :: Investment
Classifier: Topic :: Scientific/Engineering :: Mathematics
Requires-Python: >=3.9
License-File: LICENSE
Requires-Dist: numpy>=1.21.0
Requires-Dist: pandas>=1.3.0
Requires-Dist: scipy>=1.7.0
Requires-Dist: matplotlib>=3.4.0
Requires-Dist: yfinance>=0.1.70
Requires-Dist: requests>=2.25.0
Provides-Extra: viz
Requires-Dist: plotly>=5.0.0; extra == "viz"
Provides-Extra: talib
Requires-Dist: TA-Lib>=0.4.24; extra == "talib"
Provides-Extra: dev
Requires-Dist: black>=21.0.0; extra == "dev"
Requires-Dist: flake8>=3.9.0; extra == "dev"
Requires-Dist: sphinx>=4.0.0; extra == "dev"
Dynamic: license-file
